{"file":"analytics-demo.vue.mjs","mappings":"glBA6EA,MAAMA,EAAgBC,EAAI,CACxB,OAAQ,CAAC,QAAS,SAAU,OAAQ,QAAS,OAAQ,OAAO,EAC5D,SAAU,CAAC,CACT,MAAO,kBACP,KAAM,CAAC,KAAO,KAAO,KAAO,KAAO,KAAO,IAAK,EAC/C,YAAa,oBACb,gBAAiB,0BACjB,KAAM,GACN,QAAS,EACb,CAAG,CACH,CAAC,EAGKC,EAAeD,EAAI,CACvB,OAAQ,CAAC,MAAO,QAAS,UAAW,UAAW,KAAK,EACpD,SAAU,CAAC,CACT,MAAO,eACP,KAAM,CAAC,GAAI,GAAI,GAAI,GAAI,EAAE,EACzB,gBAAiB,CACf,0BACA,0BACA,0BACA,yBACA,yBACD,EACD,YAAa,CACX,oBACA,oBACA,oBACA,mBACA,mBACD,EACD,YAAa,CACjB,CAAG,CACH,CAAC,EAGKE,EAAeF,EAAI,CACvB,OAAQ,CAAC,YAAa,gBAAiB,YAAa,eAAe,EACnE,SAAU,CAAC,CACT,KAAM,CAAC,GAAI,GAAI,GAAI,EAAE,EACrB,gBAAiB,CACf,0BACA,0BACA,0BACA,wBACD,EACD,YAAa,CACX,oBACA,oBACA,oBACA,kBACD,CACL,CAAG,CACH,CAAC,EAGKG,EAAoBH,EAAI,CAC5B,OAAQ,CAAC,eAAgB,eAAgB,OAAQ,KAAM,eAAe,EACtE,SAAU,CAAC,CACT,KAAM,CAAC,GAAI,GAAI,GAAI,GAAI,CAAC,EACxB,gBAAiB,CACf,0BACA,0BACA,0BACA,yBACA,yBACD,EACD,YAAa,CACX,oBACA,oBACA,oBACA,mBACA,mBACD,CACL,CAAG,CACH,CAAC,EAGKI,EAAmBJ,EAAI,CAC3B,QAAS,CACP,OAAQ,CACN,QAAS,EACV,CACF,EACD,OAAQ,CACN,EAAG,CACD,YAAa,GACb,MAAO,CACL,SAAU,SAASK,EAAO,CACxB,OAAO,IAAI,KAAK,aAAa,OAAO,EAAE,OAAOA,CAAK,EAAI,OACvD,CACF,CACF,CACF,CACH,CAAC,EAEKC,EAAkBN,EAAI,CAC1B,QAAS,CACP,OAAQ,CACN,QAAS,EACV,CACF,EACD,OAAQ,CACN,EAAG,CACD,YAAa,GACb,MAAO,CACL,SAAU,CACX,CACF,CACF,CACH,CAAC,EAEKO,EAAkBP,EAAI,CAC1B,QAAS,CACP,OAAQ,CACN,SAAU,SACV,OAAQ,CACN,QAAS,GACT,cAAe,EAChB,CACF,CACF,CACH,CAAC,EAEKQ,EAAuBR,EAAI,CAC/B,QAAS,CACP,OAAQ,CACN,SAAU,SACV,OAAQ,CACN,QAAS,GACT,cAAe,EAChB,CACF,CACF,CACH,CAAC,EAGD,OAAAS,EAAQ,CACN,MAAO,0CACP,KAAM,CACJ,CAAE,KAAM,cAAe,QAAS,kDAAoD,EACpF,CAAE,KAAM,SAAU,QAAS,mBAAqB,CACjD,CACH,CAAC","names":["lineChartData","ref","barChartData","pieChartData","doughnutChartData","lineChartOptions","value","barChartOptions","pieChartOptions","doughnutChartOptions","useHead"],"sources":["../../../../../pages/admin/analytics-demo.vue"],"sourcesContent":["<template>\r\n  <div class=\"space-y-6\">\r\n    <!-- رأس الصفحة -->\r\n    <div class=\"flex flex-col sm:flex-row sm:items-center sm:justify-between\">\r\n      <div>\r\n        <h1 class=\"text-2xl font-bold text-gray-900\">عرض الرسوم البيانية</h1>\r\n        <p class=\"mt-1 text-sm text-gray-600\">عرض جميع أنواع الرسوم البيانية المتاحة</p>\r\n      </div>\r\n    </div>\r\n\r\n    <!-- عرض جميع أنواع الرسوم البيانية -->\r\n    <div class=\"grid grid-cols-1 lg:grid-cols-2 gap-6\">\r\n      <!-- رسم بياني خطي -->\r\n      <div class=\"bg-white rounded-lg shadow-sm border border-gray-200 p-6\">\r\n        <h3 class=\"text-lg font-semibold text-gray-900 mb-4\">رسم بياني خطي - المبيعات</h3>\r\n        <LineChart \r\n          :data=\"lineChartData\" \r\n          :height=\"300\"\r\n          :options=\"lineChartOptions\"\r\n        />\r\n      </div>\r\n\r\n      <!-- رسم بياني عمودي -->\r\n      <div class=\"bg-white rounded-lg shadow-sm border border-gray-200 p-6\">\r\n        <h3 class=\"text-lg font-semibold text-gray-900 mb-4\">رسم بياني عمودي - الحجوزات</h3>\r\n        <BarChart \r\n          :data=\"barChartData\" \r\n          :height=\"300\"\r\n          :options=\"barChartOptions\"\r\n        />\r\n      </div>\r\n\r\n      <!-- رسم بياني دائري -->\r\n      <div class=\"bg-white rounded-lg shadow-sm border border-gray-200 p-6\">\r\n        <h3 class=\"text-lg font-semibold text-gray-900 mb-4\">رسم بياني دائري - توزيع العملاء</h3>\r\n        <PieChart \r\n          :data=\"pieChartData\" \r\n          :height=\"300\"\r\n          :options=\"pieChartOptions\"\r\n        />\r\n      </div>\r\n\r\n      <!-- رسم بياني حلقي -->\r\n      <div class=\"bg-white rounded-lg shadow-sm border border-gray-200 p-6\">\r\n        <h3 class=\"text-lg font-semibold text-gray-900 mb-4\">رسم بياني حلقي - توزيع الوجهات</h3>\r\n        <DoughnutChart \r\n          :data=\"doughnutChartData\" \r\n          :height=\"300\"\r\n          :options=\"doughnutChartOptions\"\r\n        />\r\n      </div>\r\n    </div>\r\n\r\n    <!-- معلومات إضافية -->\r\n    <div class=\"bg-blue-50 rounded-lg p-6\">\r\n      <h3 class=\"text-lg font-semibold text-blue-900 mb-2\">معلومات عن الرسوم البيانية</h3>\r\n      <ul class=\"text-blue-800 space-y-2\">\r\n        <li>• جميع الرسوم البيانية تفاعلية ويمكن تكبيرها وتصغيرها</li>\r\n        <li>• تدعم اللغة العربية والاتجاه من اليمين إلى اليسار</li>\r\n        <li>• تتضمن أدوات تلميح (tooltips) لعرض التفاصيل</li>\r\n        <li>• قابلة للتخصيص من ناحية الألوان والأحجام</li>\r\n        <li>• متوافقة مع جميع أحجام الشاشات</li>\r\n      </ul>\r\n    </div>\r\n  </div>\r\n</template>\r\n\r\n<script setup>\r\nimport { LineChart, BarChart, PieChart, DoughnutChart } from '~/components/charts'\r\n\r\n// إعداد الصفحة\r\ndefinePageMeta({\r\n  layout: 'admin',\r\n  middleware: 'admin'\r\n})\r\n\r\n// بيانات الرسم البياني الخطي\r\nconst lineChartData = ref({\r\n  labels: ['يناير', 'فبراير', 'مارس', 'أبريل', 'مايو', 'يونيو'],\r\n  datasets: [{\r\n    label: 'المبيعات (ريال)',\r\n    data: [45000, 52000, 48000, 61000, 55000, 67000],\r\n    borderColor: 'rgb(59, 130, 246)',\r\n    backgroundColor: 'rgba(59, 130, 246, 0.1)',\r\n    fill: true,\r\n    tension: 0.4\r\n  }]\r\n})\r\n\r\n// بيانات الرسم البياني العمودي\r\nconst barChartData = ref({\r\n  labels: ['دبي', 'تركيا', 'ماليزيا', 'تايلاند', 'مصر'],\r\n  datasets: [{\r\n    label: 'عدد الحجوزات',\r\n    data: [25, 20, 18, 15, 12],\r\n    backgroundColor: [\r\n      'rgba(59, 130, 246, 0.8)',\r\n      'rgba(16, 185, 129, 0.8)',\r\n      'rgba(245, 158, 11, 0.8)',\r\n      'rgba(239, 68, 68, 0.8)',\r\n      'rgba(139, 92, 246, 0.8)'\r\n    ],\r\n    borderColor: [\r\n      'rgb(59, 130, 246)',\r\n      'rgb(16, 185, 129)',\r\n      'rgb(245, 158, 11)',\r\n      'rgb(239, 68, 68)',\r\n      'rgb(139, 92, 246)'\r\n    ],\r\n    borderWidth: 1\r\n  }]\r\n})\r\n\r\n// بيانات الرسم البياني الدائري\r\nconst pieChartData = ref({\r\n  labels: ['عملاء جدد', 'عملاء متكررون', 'عملاء VIP', 'عملاء محتملون'],\r\n  datasets: [{\r\n    data: [45, 30, 15, 10],\r\n    backgroundColor: [\r\n      'rgba(59, 130, 246, 0.8)',\r\n      'rgba(16, 185, 129, 0.8)',\r\n      'rgba(245, 158, 11, 0.8)',\r\n      'rgba(239, 68, 68, 0.8)'\r\n    ],\r\n    borderColor: [\r\n      'rgb(59, 130, 246)',\r\n      'rgb(16, 185, 129)',\r\n      'rgb(245, 158, 11)',\r\n      'rgb(239, 68, 68)'\r\n    ]\r\n  }]\r\n})\r\n\r\n// بيانات الرسم البياني الحلقي\r\nconst doughnutChartData = ref({\r\n  labels: ['رحلات داخلية', 'رحلات خارجية', 'عمرة', 'حج', 'رحلات ترفيهية'],\r\n  datasets: [{\r\n    data: [35, 25, 20, 15, 5],\r\n    backgroundColor: [\r\n      'rgba(59, 130, 246, 0.8)',\r\n      'rgba(16, 185, 129, 0.8)',\r\n      'rgba(245, 158, 11, 0.8)',\r\n      'rgba(239, 68, 68, 0.8)',\r\n      'rgba(139, 92, 246, 0.8)'\r\n    ],\r\n    borderColor: [\r\n      'rgb(59, 130, 246)',\r\n      'rgb(16, 185, 129)',\r\n      'rgb(245, 158, 11)',\r\n      'rgb(239, 68, 68)',\r\n      'rgb(139, 92, 246)'\r\n    ]\r\n  }]\r\n})\r\n\r\n// إعدادات الرسوم البيانية\r\nconst lineChartOptions = ref({\r\n  plugins: {\r\n    legend: {\r\n      display: false\r\n    }\r\n  },\r\n  scales: {\r\n    y: {\r\n      beginAtZero: true,\r\n      ticks: {\r\n        callback: function(value) {\r\n          return new Intl.NumberFormat('ar-SA').format(value) + ' ريال'\r\n        }\r\n      }\r\n    }\r\n  }\r\n})\r\n\r\nconst barChartOptions = ref({\r\n  plugins: {\r\n    legend: {\r\n      display: false\r\n    }\r\n  },\r\n  scales: {\r\n    y: {\r\n      beginAtZero: true,\r\n      ticks: {\r\n        stepSize: 5\r\n      }\r\n    }\r\n  }\r\n})\r\n\r\nconst pieChartOptions = ref({\r\n  plugins: {\r\n    legend: {\r\n      position: 'bottom',\r\n      labels: {\r\n        padding: 15,\r\n        usePointStyle: true\r\n      }\r\n    }\r\n  }\r\n})\r\n\r\nconst doughnutChartOptions = ref({\r\n  plugins: {\r\n    legend: {\r\n      position: 'bottom',\r\n      labels: {\r\n        padding: 15,\r\n        usePointStyle: true\r\n      }\r\n    }\r\n  }\r\n})\r\n\r\n// SEO والميتا\r\nuseHead({\r\n  title: 'عرض الرسوم البيانية - Wonder Land Admin',\r\n  meta: [\r\n    { name: 'description', content: 'عرض جميع أنواع الرسوم البيانية المتاحة في النظام' },\r\n    { name: 'robots', content: 'noindex, nofollow' }\r\n  ]\r\n})\r\n</script>\r\n"],"version":3}