{"expires":1759241997662,"value":{"code":200,"headers":{"etag":"W/\"O26rz5TVi9\"","last-modified":"Tue, 23 Sep 2025 14:19:57 GMT","cache-control":"s-maxage=604800, stale-while-revalidate"},"body":{"prefix":"material-symbols","icons":{"delete":{"body":"<path fill=\"currentColor\" d=\"M7 21q-.825 0-1.412-.587T5 19V6H4V4h5V3h6v1h5v2h-1v13q0 .825-.587 1.413T17 21zm2-4h2V8H9zm4 0h2V8h-2z\"/>"},"image":{"body":"<path fill=\"currentColor\" d=\"M5 21q-.825 0-1.412-.587T3 19V5q0-.825.588-1.412T5 3h14q.825 0 1.413.588T21 5v14q0 .825-.587 1.413T19 21zm1-4h12l-3.75-5l-3 4L9 13z\"/>"},"play-arrow":{"body":"<path fill=\"currentColor\" d=\"M8 19V5l11 7z\"/>"}},"lastModified":1744437352,"width":24,"height":24}},"mtime":1758637197667,"integrity":"UsGBZBr1w0"}